RobustGibbs/.DS_Store
RobustGibbs/IQR.py
RobustGibbs/MAD.py
RobustGibbs/Quantile.py
RobustGibbs/__init__.py
RobustGibbs/postertior_sample.py
RobustGibbs/truncated.py
robustgibbs-0.0.7.dist-info/METADATA
robustgibbs-0.0.7.dist-info/WHEEL
robustgibbs-0.0.7.dist-info/licenses/LICENSE.txt
robustgibbs-0.0.7.dist-info/RECORD
