Metadata-Version: 2.1
Name: RobustGibbs
Version: 0.0.7
Summary: Package for Gibbs Sampling with Robust Statistics.
Project-URL: Homepage, https://github.com/pypa/sampleproject
Project-URL: Bug Tracker, https://github.com/pypa/sampleproject/issues
Author-email: Antoine Luciano <antoine.luciano@dauphine.psl.eu>
License-File: LICENSE.txt
Classifier: License :: OSI Approved :: MIT License
Classifier: Operating System :: OS Independent
Classifier: Programming Language :: Python :: 3
Requires-Python: >=3.7
